{
    "jobs": [
        {
            "id": 0,
            "p": 51,
            "w": 2,
            "d": 405,
            "pri": 0.0392156862745098
        },
        {
            "id": 1,
            "p": 84,
            "w": 4,
            "d": 315,
            "pri": 0.047619047619047616
        },
        {
            "id": 2,
            "p": 7,
            "w": 2,
            "d": 577,
            "pri": 0.2857142857142857
        },
        {
            "id": 3,
            "p": 10,
            "w": 9,
            "d": 360,
            "pri": 0.9
        },
        {
            "id": 4,
            "p": 69,
            "w": 7,
            "d": 440,
            "pri": 0.10144927536231885
        },
        {
            "id": 5,
            "p": 13,
            "w": 1,
            "d": 506,
            "pri": 0.07692307692307693
        },
        {
            "id": 6,
            "p": 47,
            "w": 10,
            "d": 365,
            "pri": 0.2127659574468085
        },
        {
            "id": 7,
            "p": 75,
            "w": 2,
            "d": 568,
            "pri": 0.02666666666666667
        },
        {
            "id": 8,
            "p": 8,
            "w": 4,
            "d": 352,
            "pri": 0.5
        },
        {
            "id": 9,
            "p": 65,
            "w": 10,
            "d": 584,
            "pri": 0.15384615384615385
        },
        {
            "id": 10,
            "p": 28,
            "w": 1,
            "d": 449,
            "pri": 0.03571428571428571
        },
        {
            "id": 11,
            "p": 5,
            "w": 10,
            "d": 578,
            "pri": 2.0
        },
        {
            "id": 12,
            "p": 12,
            "w": 10,
            "d": 641,
            "pri": 0.8333333333333334
        },
        {
            "id": 13,
            "p": 56,
            "w": 7,
            "d": 384,
            "pri": 0.125
        },
        {
            "id": 14,
            "p": 54,
            "w": 1,
            "d": 344,
            "pri": 0.018518518518518517
        }
    ],
    "meta": {
        "L": 0.8,
        "R": 0.6,
        "P": 584,
        "deadline_range": [
            292,
            642
        ]
    }
}